configs/__init__.py
tests/__init__.py
tests/conftest.py
tests/test_configs.py
tests/test_datamodules.py
tests/helpers/__init__.py
tests/helpers/package_available.py
tests/helpers/run_if.py
tests/helpers/run_sh_command.py
lightningtrain-0.0.4.dist-info/LICENSE
lightningtrain-0.0.4.dist-info/METADATA
lightningtrain-0.0.4.dist-info/WHEEL
lightningtrain-0.0.4.dist-info/entry_points.txt
lightningtrain-0.0.4.dist-info/top_level.txt
lightningtrain-0.0.4.dist-info/RECORD
