Metadata-Version: 2.1
Name: lightningtrain
Version: 0.0.4
Summary: PyTorch Lightning Project Setup
Home-page: https://github.com/dlwizard/lightningtrain.git
Author: Santu Hazra
Author-email: ec.santuh@gmail.com
Requires-Python: >=3.10.6
License-File: LICENSE
Requires-Dist: lightning
Requires-Dist: hydra-core
